{
  "project_info": {
    "project_number": "934828416095",
    "project_id": "fitpin-94f27",
    "storage_bucket": "fitpin-94f27.appspot.com"
  },
  "client": [
    {
      "client_info": {
        "mobilesdk_app_id": "1:934828416095:android:267e24a1f80f72bae8cfea",
        "android_client_info": {
          "package_name": "com.nativetest"
        }
      },
      "oauth_client": [
        {
          "client_id": "934828416095-kgj977r6ov872hr4flutvj15csftd528.apps.googleusercontent.com",
          "client_type": 1,
          "android_info": {
            "package_name": "com.nativetest",
            "certificate_hash": "d28c257d43ab709035ba72e0e86c69f500c0f16e"
          }
        },
        {
          "client_id": "934828416095-s1b8nvithrntut57d35gnldpurudlfqk.apps.googleusercontent.com",
          "client_type": 3
        }
      ],
      "api_key": [
        {
          "current_key": "AIzaSyDuLIRYe_rGoPJAgn9U4nE1_79SXcZZODA"
        }
      ],
      "services": {
        "appinvite_service": {
          "other_platform_oauth_client": [
            {
              "client_id": "934828416095-s1b8nvithrntut57d35gnldpurudlfqk.apps.googleusercontent.com",
              "client_type": 3
            }
          ]
        }
      }
    }
  ],
  "configuration_version": "1"
}